sysom_pai_client/__init__.py
sysom_pai_client/client.py
sysom_pai_client/sysom_signal_pb2.py
sysom_pai_client/sysom_signal_pb2_grpc.py
sysom_pai_client-1.0.0.dev15.dist-info/METADATA
sysom_pai_client-1.0.0.dev15.dist-info/WHEEL
sysom_pai_client-1.0.0.dev15.dist-info/entry_points.txt
sysom_pai_client-1.0.0.dev15.dist-info/top_level.txt
sysom_pai_client-1.0.0.dev15.dist-info/RECORD
